pihole6api/__init__.py
pihole6api/actions.py
pihole6api/client.py
pihole6api/client_management.py
pihole6api/config.py
pihole6api/conn.py
pihole6api/dhcp.py
pihole6api/dns_control.py
pihole6api/domain_management.py
pihole6api/ftl_info.py
pihole6api/group_management.py
pihole6api/list_management.py
pihole6api/metrics.py
pihole6api/network_info.py
pihole6api-0.2.0.dist-info/licenses/LICENSE
pihole6api-0.2.0.dist-info/METADATA
pihole6api-0.2.0.dist-info/WHEEL
pihole6api-0.2.0.dist-info/top_level.txt
pihole6api-0.2.0.dist-info/RECORD
