Metadata-Version: 2.4
Name: pihole6api
Version: 0.2.0
Summary: Python API Client for Pi-hole 6
Author-email: Shane Barbetta <shane@barbetta.me>
License: MIT
Project-URL: Homepage, https://github.com/sbarbett/pihole6api
Project-URL: Documentation, https://github.com/sbarbett/pihole6api
Project-URL: Source, https://github.com/sbarbett/pihole6api
Project-URL: Issues, https://github.com/sbarbett/pihole6api/issues
Keywords: pihole,dns,adblocking,api,client
Classifier: Development Status :: 4 - Beta
Classifier: Intended Audience :: Developers
Classifier: License :: OSI Approved :: MIT License
Classifier: Programming Language :: Python :: 3
Classifier: Programming Language :: Python :: 3.8
Classifier: Programming Language :: Python :: 3.9
Classifier: Programming Language :: Python :: 3.10
Classifier: Programming Language :: Python :: 3.11
Classifier: Programming Language :: Python :: 3.12
Requires-Python: >=3.8
License-File: LICENSE
Requires-Dist: requests>=2.26.0
Dynamic: license-file
